{
  "name": "Henrietta Joseph",
  "age": 48,
  "address": {
    "street": "Juhduf View",
    "city": "Mihatepo",
    "state": "WY",
    "zip": "95471"
  },
  "contact": {
    "phone": "(565) 989-9741",
    "servicePhone": "800411862"
  },
  "birthday": "2000-05-25T08:14:23.868Z",
  "ip": "211.202.253.229",
  "foo": "bar",
  "profile": {
    "about": "Nawu uw hakfukzu li mewek tidifil nub ozu ezrukin tu il ge ebo ule hokci tajhembiz. Dikwo daw enawapde sawap ti ina ecifi vohnapeb wi cibuti lubdo piz hati alwuij abo fezolgeh miz. Fobib magecer ridmi hekit hi ahjiszi hidba luwci nog hipunu abukof bimof asa. Dov ifoja mekguk rih avo veku poez be varuzu abe oparu pueroaj tiz luam vom ve sucwudvu kiuw. Fit maivwob di jal betep hohgif ciltofe batove gibtekpuv kupetze nulurgej vomir cuuzoda.",
    "bio": "Wubeb de umle din fut soazdik wedicowe kew te feh ocgezmu doleh fatat naw. Sina gipgomru jid itoju cenwe buuz nefjo wasap ujusuvvi pecowtof patevsaf kisil. Ipa isimor anomapib neh luoge ebi ipa umge ohvuve kama okoleglu mo vanpufi emecuzde zu. Lirzas soh nil tumfivlu fuj ivuoku vo mihumki pulbi hesofde lem soc zuftefig jolge. Alacinim hefji bo sob newuesi uwzaud jewar ho wentak tilupil ca ivawgip kebkatjof cegusfej zit cur. Gec budpocuv ca nokem nos suw egeggi iwzo gibubsav nivnamte vomjitag uw fazwihra ke lepaop zawo zaszues vesub."
  },
  "apiKey": "783c8c675a46d0d3471716ef5b6e9bf87f426b7c191e48ff540a2363d0ac3a8b",
  "currency": {
    "code": "GTQ",
    "name": "Guatemala Quetzal"
  }
}