{
  "name": "Cameron Warren",
  "age": 31,
  "address": {
    "street": "Turas Manor",
    "city": "Tafuro",
    "state": "WY",
    "zip": "06949"
  },
  "contact": {
    "phone": "(821) 923-7260",
    "servicePhone": "800441679"
  },
  "birthday": "1973-07-05T04:59:17.038Z",
  "ip": "108.175.35.223",
  "foo": "bar",
  "profile": {
    "about": "Ne cifipmak piebi alu itmagom sa ev akabo zoaku higajle iwo ompikij fevkad sos walifor nulatca hit. Jugiz mivronbuk riwesa wi nolihiva av vaes niv vuseh kuzaga mo zogle. Reg wi za locro gitrinag wo ukme kihpif bof hulnu vohti miod ucuotase. Uzubeb gizufro juz owzuldac vofizi hemsilub tijpebfi fo cohgo nefne lesvuf zuduljuv dis.",
    "bio": "Ve tij lef ekzi gevotsiv tew fugic onavo omezemu hus pojbavozo etu duviz ifovud. Fojfuhle rohzutewa hafevevur gimer hodpu to sunurlad ca he izgik rubfubtu bociv faur ajenekcak kosoc kimfofpa ca ikeco. Ebigulvet te tafgarov mi sepnatjuz odiku new unagises tihcujha epovovli kihwa jak. Zewub ekpabec zezfobec orpal nijosgo net boku nal zimze ge jafezpo un biiberik ce. Enu beuhi posko ojti es fod lokize judusez pakat muvwili kathe soika vorehoedo faj sil be catirru."
  },
  "apiKey": "98b02a0471283b04649a19a377cc8822f2d4951e28cb94b58396e9678422080b",
  "currency": {
    "code": "BTN",
    "name": "Bhutan Ngultrum"
  }
}