{
  "name": "Adeline Williamson",
  "age": 63,
  "address": {
    "street": "Uhulo Key",
    "city": "Kewocme",
    "state": "NM",
    "zip": "84313"
  },
  "contact": {
    "phone": "(411) 841-2621",
    "servicePhone": "800257787"
  },
  "birthday": "1996-02-05T19:55:25.177Z",
  "ip": "59.189.84.98",
  "foo": "bar",
  "profile": {
    "about": "Ofabiv nagasra oreer itecazo tol otvof wof tadodo hare vevojilu jonbahvar kecuselah fabunu. Et jivotla ce bo epuwe nijceju ovikaz duco efpecto tin wohi al gag uc loepfi cuniwko. Zoplejwaw zecpu zuw turuw jihete ru holjikul je cout avi zu satvu wi.",
    "bio": "Pekun samat si di defkakede de mimsew pislunoh revbu ko bebababe we civhe. Ujowuc heutza woj zur wusjin uhesegla de hez mavoof nek sejijdof datiru mafsu ko nu guko mulecwuf. Firuwpa cavomite om vo ji sisewog izuuj cengig gur matec von tiospon dapife som."
  },
  "apiKey": "d575c0400bcf1ae2864b4b9ef563a2bdab4b68f8cb152e2f25ef020c8e922629",
  "currency": {
    "code": "CHF",
    "name": "Switzerland Franc"
  }
}